RunSpiders/__init__.py
RunSpiders/configuration.py
RunSpiders/utils.py
RunSpiders/book/__init__.py
RunSpiders/book/web_fiction.py
RunSpiders/music/__init__.py
RunSpiders/others/__init__.py
RunSpiders/others/for_github.py
RunSpiders/templates/__init__.py
RunSpiders/video/__init__.py
RunSpiders/video/base/__init__.py
RunSpiders/video/base/m3u8.py
RunSpiders/video/base/mp4.py
RunSpiders/video/webs/__init__.py
RunSpiders/video/webs/jav.py
RunSpiders/video/webs/pornhub.py
RunSpiders/video/webs/vk.py
RunSpiders-1.0.8.dist-info/LICENSE
RunSpiders-1.0.8.dist-info/METADATA
RunSpiders-1.0.8.dist-info/WHEEL
RunSpiders-1.0.8.dist-info/top_level.txt
RunSpiders-1.0.8.dist-info/RECORD
