Metadata-Version: 2.1
Name: RunSpiders
Version: 1.0.8
Summary: A python library contains many powerful web crawlers.
Home-page: https://github.com/Ijustwantyouhappy/RunSpiders
Author: Ijustwantyouhappy
Author-email: 
License: MIT
Project-URL: GitHub, https://github.com/Ijustwantyouhappy/RunSpiders
Project-URL: Source, https://github.com/Ijustwantyouhappy/RunSpiders
Keywords: spiders
Platform: UNKNOWN
Classifier: Environment :: Web Environment
Classifier: Intended Audience :: Developers
Classifier: License :: OSI Approved :: MIT License
Classifier: Topic :: Software Development :: Libraries :: Python Modules
Classifier: Programming Language :: Python :: 3
Requires-Python: >=3.5
Requires-Dist: requests
Requires-Dist: beautifulsoup4
Requires-Dist: jinja2
Requires-Dist: pycryptodome
Requires-Dist: gevent
Requires-Dist: tqdm
Requires-Dist: selenium
Requires-Dist: js2py
Requires-Dist: prettytable
